MANIFEST.in
README.rst
setup.py
aliyun_python_sdk_uis_inner.egg-info/PKG-INFO
aliyun_python_sdk_uis_inner.egg-info/SOURCES.txt
aliyun_python_sdk_uis_inner.egg-info/dependency_links.txt
aliyun_python_sdk_uis_inner.egg-info/requires.txt
aliyun_python_sdk_uis_inner.egg-info/top_level.txt
aliyunsdkuis_inner/__init__.py
aliyunsdkuis_inner/request/__init__.py
aliyunsdkuis_inner/request/v20180821/InnerCreateTerraformTaskRequest.py
aliyunsdkuis_inner/request/v20180821/InnerDescribeHighPriorityIpRequest.py
aliyunsdkuis_inner/request/v20180821/InnerDescribeResourceGroupRequest.py
aliyunsdkuis_inner/request/v20180821/InnerDescribeUisAreaIdsRequest.py
aliyunsdkuis_inner/request/v20180821/InnerDescribeUisBoardResourceRequest.py
aliyunsdkuis_inner/request/v20180821/InnerDescribeUisOffResourceRequest.py
aliyunsdkuis_inner/request/v20180821/InnerDescribeUisTopologyRequest.py
aliyunsdkuis_inner/request/v20180821/InnerDescribeUisesRequest.py
aliyunsdkuis_inner/request/v20180821/InnerEnableUisOffAreaRequest.py
aliyunsdkuis_inner/request/v20180821/__init__.py